README.md
setup.py
mlcycle/__init__.py
mlcycle/apierror.py
mlcycle/client.py
mlcycle/environment.py
mlcycle/fragment.py
mlcycle/job.py
mlcycle/project.py
mlcycle/scheduler.py
mlcycle/worker.py
mlcycle.egg-info/PKG-INFO
mlcycle.egg-info/SOURCES.txt
mlcycle.egg-info/dependency_links.txt
mlcycle.egg-info/requires.txt
mlcycle.egg-info/top_level.txt